mast/__init__.py
mast/_version.py
mast/mast_client.py
mast/geom/__init__.py
mast/geom/geomBolo.py
mast/geom/geomEfitElements.py
mast/geom/geomEfitLimiter.py
mast/geom/geomElm.py
mast/geom/geomFluxloops.py
mast/geom/geomHaloSaddle.py
mast/geom/geomLangmuir.py
mast/geom/geomPickup.py
mast/geom/geomRog.py
mast/geom/geomTileSurfaceUtils.py
mast/geom/geometry.py
mast/geom/geometryClient.py
mast/geom/geometryFiles.py
mast/geom/geometryUtils.py
mast/geom/signalGeometry.py
mast/geom/structuredWritable.py
mast/geom/tile_surface_normal_vectors/N1.csv
mast/geom/tile_surface_normal_vectors/N1_no_shift_surface_normals.csv
mast/geom/tile_surface_normal_vectors/N1_shift_surface_normals.csv
mast/geom/tile_surface_normal_vectors/N2.csv
mast/geom/tile_surface_normal_vectors/N2_no_shift_surface_normals.csv
mast/geom/tile_surface_normal_vectors/N2_shift_surface_normals.csv
mast/geom/tile_surface_normal_vectors/T1.csv
mast/geom/tile_surface_normal_vectors/T1_no_shift_surface_normals.csv
mast/geom/tile_surface_normal_vectors/T1_shift_surface_normals.csv
mast/geom/tile_surface_normal_vectors/T2.csv
mast/geom/tile_surface_normal_vectors/T2_SN.csv
mast/geom/tile_surface_normal_vectors/T2_no_shift_surface_normals.csv
mast/geom/tile_surface_normal_vectors/T2_shift_surface_normals.csv
mast/geom/tile_surface_normal_vectors/T3.csv
mast/geom/tile_surface_normal_vectors/T3_SN.csv
mast/geom/tile_surface_normal_vectors/T3_no_shift_surface_normals.csv
mast/geom/tile_surface_normal_vectors/T3_shift_surface_normals.csv
mast/geom/tile_surface_normal_vectors/T4.csv
mast/geom/tile_surface_normal_vectors/T4_SN.csv
mast/geom/tile_surface_normal_vectors/T4_no_shift_surface_normals.csv
mast/geom/tile_surface_normal_vectors/T4_shift_surface_normals.csv
mast/geom/tile_surface_normal_vectors/T5A.csv
mast/geom/tile_surface_normal_vectors/T5A_no_shift_surface_normals.csv
mast/geom/tile_surface_normal_vectors/T5A_shift_surface_normals.csv
mast/geom/tile_surface_normal_vectors/T5B.csv
uda_mast-1.3.14.dist-info/METADATA
uda_mast-1.3.14.dist-info/WHEEL
uda_mast-1.3.14.dist-info/top_level.txt
uda_mast-1.3.14.dist-info/RECORD
