Metadata-Version: 2.4
Name: uda-mast
Version: 1.3.14
Summary: MAST python wrapper for UDA
Author-email: Lucy Kogan <lucy.kogan@ukaea.uk>
License: Apache-2.0 license
Project-URL: homepage, https://users.mastu.ukaea.uk/data-access-and-tools/
Project-URL: source, https://git.ccfe.ac.uk/MAST-U/mastcodes
Project-URL: issues, https://git.ccfe.ac.uk/MAST-U/mastcodes/-/issues
Project-URL: documentation, https://users.mastu.ukaea.uk/data-access-and-tools/data-access/uda/
Classifier: Intended Audience :: Science/Research
Classifier: Programming Language :: Python :: 3
Classifier: Programming Language :: Python :: 3 :: Only
Classifier: Operating System :: POSIX :: Linux
Classifier: Operating System :: MacOS :: MacOS X
Classifier: Operating System :: Microsoft :: Windows
Requires-Dist: shapely
Requires-Dist: pandas
Requires-Dist: numpy
Requires-Dist: scipy
Requires-Dist: pyuda
